Workbook

Sheet Реестр
A1: № | B1: Дата | C1: Категория | D1: Номер документа / Описание | E1: Сумма, $
A2: 1 | B2: — | C2: Аренда | D2: Депозит + первый месяц (Lease Agreement) | E2: 6943
A3: 2 | B3: — | C3: Аренда | D3: Аренда за весь срок (54 месяца) — имеются копии банковских чеков | E3: 54000
A4: 3 | B4: — | C4: Электричество (FPL) | D4: Депозит за подключение | E4: 400
A5: 4 | B5: — | C5: Электричество (FPL) | D5: Ежемесячные платежи (18 мес. × ~$200) | E5: 3600
A6: 5 | B6: — | C6: Мебель и оборудование | D6: Полный комплект мебели (основной заказ) | E6: 11400
A7: 6 | B7: — | C7: Мебель и оборудование | D7: Центральная барная стойка (своими руками) | E7: 1500
A8: 7 | B8: 19.02.2026 | C8: Мебель и оборудование | D8: IKEA BESTÅ комплектующие (Picking List) | E8: 450
A9: 8 | B9: — | C9: Мебель и оборудование | D9: Стол + 7 стульев | E9: 455
A10: 9 | B10: — | C10: Мебель и оборудование | D10: Сборка мебели (услуги установщика) | E10: 1400
A11: 10 | B11: 03.12.2024 | C11: Оборудование | D11: Кондиционер + установка (чек #1362) | E11: 1420
A12: 11 | B12: 22.04.2022 | C12: Оборудование | D12: Водонагреватель безбачный (Invoice #148784) | E12: 240.75
A13: 12 | B13: 15.03.2026 | C13: Оборудование | D13: Ледогенератор коммерческий (Order #CTCCF7VBPA) | E13: 291.76
... A52: 51 | B52: 15.05.2025 | C52: Чай (товар для продажи) | D52: 15 видов тайваньского чая + доставка DHL (Yama Dai Tea, YMT/0089/25) | E52: 1306.98
D53: ИТОГО: | E53: =SUM(E2:E52)

Sheet Сводка по категориям
A1: Категория | B1: Сумма, $ | C1: Доля, %
A2: Аренда | B2: =SUMIF(Реестр!C:C,A2,Реестр!E:E) | C2: =B2/$B$15
A3: Электричество (FPL) | B3: =SUMIF(Реестр!C:C,A3,Реестр!E:E) | C3: =B3/$B$15
A4: Мебель и оборудование | B4: =SUMIF(Реестр!C:C,A4,Реестр!E:E) | C4: =B4/$B$15
A5: Оборудование | B5: =SUMIF(Реестр!C:C,A5,Реестр!E:E) | C5: =B5/$B$15
A6: Освещение | B6: =SUMIF(Реестр!C:C,A6,Реестр!E:E) | C6: =B6/$B$15
A7: Ремонт и отделка | B7: =SUMIF(Реестр!C:C,A7,Реестр!E:E) | C7: =B7/$B$15
A8: Лицензии и разрешения | B8: =SUMIF(Реестр!C:C,A8,Реестр!E:E) | C8: =B8/$B$15
A9: Брендинг и маркетинг | B9: =SUMIF(Реестр!C:C,A9,Реестр!E:E) | C9: =B9/$B$15
A10: Парковка | B10: =SUMIF(Реестр!C:C,A10,Реестр!E:E) | C10: =B10/$B$15
A11: Пожарная безопасность | B11: =SUMIF(Реестр!C:C,A11,Реестр!E:E) | C11: =B11/$B$15
A12: Хозяйственные товары | B12: =SUMIF(Реестр!C:C,A12,Реестр!E:E) | C12: =B12/$B$15
A13: Чайная посуда | B13: =SUMIF(Реестр!C:C,A13,Реестр!E:E) | C13: =B13/$B$15
A14: Чай (товар для продажи) | B14: =SUMIF(Реестр!C:C,A14,Реестр!E:E) | C14: =B14/$B$15
A15: ИТОГО: | B15: =SUM(B2:B14) | C15: 1
